{
  "id": "7",
  "name": "QuantileDiscretizer",
  "type": "ml-transformer",
  "description": "QuantileDiscretizer takes a column with continuous features and outputs a column with binned categorical features.",
  "nodeClass": "fire.nodes.ml.NodeQuantileDiscretizer",
  "fields" : [
    {"name":"inputCol", "value":"", "widget": "variable", "title": "Input Column", "description": "The Input column name", "datatypes":["double"]},

    {"name":"outputCol", "value":"", "widget": "textfield", "title": "Output Column", "description": "Output column name", "datatypes":["double"]},

    {"name":"numBuckets", "value":"2", "widget": "textfield", "title": "NumBuckets", "description": "Maximum number of buckets (quantiles or categories) into which the data points are grouped. Must be >= 2.", "datatypes":["integer"]}

  ]
}
